compassdock/__init__.py
compassdock/compass.py
compassdock/compassdock.py
compassdock/config.py
compassdock/esm_processing.py
compassdock/finetune.py
compassdock/inference_wrap.py
compassdock/training.py
compassdock/AA_Score_Tool/AA_Score.py
compassdock/AA_Score_Tool/__init__.py
compassdock/AA_Score_Tool/interaction_components/__init__.py
compassdock/AA_Score_Tool/interaction_components/config.py
compassdock/AA_Score_Tool/interaction_components/detection.py
compassdock/AA_Score_Tool/interaction_components/plinteraction.py
compassdock/AA_Score_Tool/interaction_components/utils.py
compassdock/AA_Score_Tool/utils/__init__.py
compassdock/AA_Score_Tool/utils/electrostatic.py
compassdock/AA_Score_Tool/utils/get_pocket_by_biopandas.py
compassdock/AA_Score_Tool/utils/hbonds.py
compassdock/AA_Score_Tool/utils/hydrophobic.py
compassdock/AA_Score_Tool/utils/vdw.py
compassdock/DiffDock/__init__.py
compassdock/DiffDock/evaluate.py
compassdock/DiffDock/inference.py
compassdock/DiffDock/inference_new.py
compassdock/DiffDock/train.py
compassdock/DiffDock/confidence/__init__.py
compassdock/DiffDock/confidence/confidence_train.py
compassdock/DiffDock/confidence/dataset.py
compassdock/DiffDock/data/splits/finetune/split.py
compassdock/DiffDock/datasets/__init__.py
compassdock/DiffDock/datasets/conformer_matching.py
compassdock/DiffDock/datasets/constants.py
compassdock/DiffDock/datasets/dataloader.py
compassdock/DiffDock/datasets/esm_embedding_preparation.py
compassdock/DiffDock/datasets/esm_embeddings_to_pt.py
compassdock/DiffDock/datasets/loader.py
compassdock/DiffDock/datasets/moad.py
compassdock/DiffDock/datasets/parse_chi.py
compassdock/DiffDock/datasets/pdb_dock.py
compassdock/DiffDock/datasets/pdbbind.py
compassdock/DiffDock/datasets/process_mols.py
compassdock/DiffDock/datasets/sidechain_esm_embeddings_to_pt.py
compassdock/DiffDock/models/__init__.py
compassdock/DiffDock/models/aa_model.py
compassdock/DiffDock/models/cg_model.py
compassdock/DiffDock/models/layers.py
compassdock-0.1.4.dist-info/LICENSE
compassdock-0.1.4.dist-info/METADATA
compassdock-0.1.4.dist-info/WHEEL
compassdock-0.1.4.dist-info/top_level.txt
compassdock-0.1.4.dist-info/RECORD
