Metadata-Version: 2.1
Name: compassdock
Version: 0.1.4
Summary: A comprehensive accurate assessment approach for deep learning based molecular docking
Author-email: Ahmet Sarigun <Ahmet.Sariguen@mdc-berlin.de>
Maintainer-email: Ahmet Sarigun <Ahmet.Sariguen@mdc-berlin.de>
License: Modified MIT License for Academic and Non-Commercial Use
Classifier: Development Status :: 3 - Alpha
Classifier: Topic :: Scientific/Engineering :: Bio-Informatics
Classifier: Programming Language :: Python :: 3.11
Requires-Python: <3.12,>=3.11
License-File: LICENSE
Requires-Dist: torch ==2.3.0
Requires-Dist: torchvision ==0.18.0
Requires-Dist: torchaudio ==2.3.0
Requires-Dist: PyYAML
Requires-Dist: scipy
Requires-Dist: networkx[default]
Requires-Dist: biopython
Requires-Dist: rdkit-pypi
Requires-Dist: e3nn
Requires-Dist: spyrmsd
Requires-Dist: pandas ==2.0.0
Requires-Dist: biopandas
Requires-Dist: prody ==2.4.1
Requires-Dist: torch-geometric ==2.5.3
Requires-Dist: rdkit ==2023.9.6
Requires-Dist: py3dmol ==2.1.0
Requires-Dist: prolif ==2.0.3
Requires-Dist: pybel ==0.15.5
Requires-Dist: seaborn
Requires-Dist: omegaconf
Requires-Dist: ml-collections
Requires-Dist: dm-tree
Requires-Dist: modelcif ==1.0
Requires-Dist: einops ==0.8.0
